pygount/__init__.py
pygount/analysis.py
pygount/command.py
pygount/common.py
pygount/lexers.py
pygount/summary.py
pygount/write.py
pygount/xmldialect.py
rich_pygount-1.3.4.dist-info/LICENSE.txt
rich_pygount-1.3.4.dist-info/METADATA
rich_pygount-1.3.4.dist-info/WHEEL
rich_pygount-1.3.4.dist-info/entry_points.txt
rich_pygount-1.3.4.dist-info/top_level.txt
rich_pygount-1.3.4.dist-info/RECORD
