Metadata-Version: 2.1
Name: rich-pygount
Version: 1.3.4
Summary: count source lines of code (SLOC) using pygments
Home-page: https://github.com/roskakori/pygount
Author: Thomas Aglassinger
Author-email: roskakori@users.sourceforge.net
License: BSD
Project-URL: Documentation, https://pygount.readthedocs.io/
Project-URL: Issue Tracker, https://github.com/roskakori/pygount/issues
Keywords: code analysis,count,SLOC
Platform: UNKNOWN
Classifier: Development Status :: 5 - Production/Stable
Classifier: Environment :: Console
Classifier: Intended Audience :: Developers
Classifier: License :: OSI Approved :: BSD License
Classifier: Natural Language :: English
Classifier: Operating System :: OS Independent
Classifier: Programming Language :: Python :: 3 :: Only
Classifier: Programming Language :: Python :: 3.6
Classifier: Programming Language :: Python :: 3.7
Classifier: Programming Language :: Python :: 3.8
Classifier: Programming Language :: Python :: 3.9
Classifier: Topic :: Software Development
Requires-Python: >=3.6
Requires-Dist: pygments (>=2.0)
Requires-Dist: rich (>=10.16.1)
